omdb/__init__.py
omdb/__pkg__.py
omdb/_compat.py
omdb/api.py
omdb/client.py
omdb-0.10.1.dist-info/AUTHORS.rst
omdb-0.10.1.dist-info/LICENSE.rst
omdb-0.10.1.dist-info/METADATA
omdb-0.10.1.dist-info/WHEEL
omdb-0.10.1.dist-info/top_level.txt
omdb-0.10.1.dist-info/RECORD
