Metadata-Version: 1.1
Name: omdb
Version: 0.10.1
Summary: Python wrapper for OMDb API: http://www.omdbapi.com/
Home-page: https://github.com/dgilland/omdb.py
Author: Derrick Gilland
Author-email: dgilland@gmail.com
License: MIT License
Keywords: omdb imdb movies
Platform: UNKNOWN
Classifier: Development Status :: 4 - Beta
Classifier: Environment :: Web Environment
Classifier: Intended Audience :: Developers
Classifier: Operating System :: OS Independent
Classifier: Programming Language :: Python
Classifier: License :: OSI Approved :: MIT License
Classifier: Programming Language :: Python
Classifier: Programming Language :: Python :: 2
Classifier: Programming Language :: Python :: 2.7
Classifier: Programming Language :: Python :: 3
Classifier: Programming Language :: Python :: 3.4
Classifier: Programming Language :: Python :: 3.5
Classifier: Programming Language :: Python :: 3.6
Classifier: Programming Language :: Python :: 3.7
